{
    "navItems": [
      {
        "name": "Styles",
        "subnavItems": [
          {
            "name": "A to Z content style guide"
          },
          {
            "name": "Colour palettes"
          },
          {
            "name": "Icons"
          },
          {
            "name": "Images"
          },
          {
            "name": "Layout"
          },
          {
            "name": "Maps"
          },
          {
            "name": "Typography"
          },
          {
            "name": "Utility classes"
          }
        ]
      },
      {
        "name": "Components",
        "subnavItems": [
          {
            "name": "Accordion"
          },
          {
            "name": "Breadcrumb"
          },
          {
            "name": "Buttons"
          },
          {
            "name": "Content card"
          },
          {
            "name": "Details"
          },
          {
            "name": "Document"
          },				          
          {
            "name": "File download"
          },
          {
            "name": "Form elements"
          },
          {
            "name": "Hub header"
          },
          {
            "name": "Inset text"
          },
          {
            "name": "In-text step"
          },
          {
            "name": "Links"
          },
          {
            "name": "Lists"
          },
          {
            "name": "Loader"
          },
          {
            "name": "Message"
          },
          {
            "name": "Page contents"
          },
          {
            "name": "Page header"
          },
          {
            "name": "Phase indicator"
          },
          {
            "name": "Portfolio leads"
          },
          {
            "name": "Share"
          },
          {
            "name": "Table"
          },
          {
            "name": "Tag"
          },
          {
            "name": "Warning text"
          }
        ]
      },
      {
        "name": "Patterns",
        "subnavItems": [
          {
            "name": "Autocomplete"
          },
          {
            "name": "Banner"
          },
          {
            "name": "Board Members"
          },
          {
            "name": "Cookies"
          },
          {
            "name": "Contact details"
          },
          {
            "name": "Feedback loop"
          },
          {
            "name": "Footer"
          },
          {
            "name": "Header"
          },
          {
            "name": "Header and footer"
          },
          {
            "name": "Question form"
          },
          {
            "name": "Search"
          }
        ]
      },
      {
        "name": "Templates"
      }
    ],
    "colors": {
        "brand": [
			{ 
				"varName": "wmFurnaceOrange",
				"name": "WM Furnace Orange" 
			},
			{ 
				"varName": "steelBlueBg", 
				"name": "Steel Blue" 
			},
			{ 
				"varName": "primaryDudleyBrick", 
				"name": "Dudley Brick - Primary" 
			},
			{ 
				"varName": "primaryAcocksGreen", 
				"name": "Acocks Green - Primary" 
			},
			{ 
				"varName": "primaryCoventrySky", 
				"name": "Coventry Sky - Primary" 
			},
			{ 
				"varName": "primaryRowleyRouge", 
				"name": "Rowley Rouge - Primary" 
			},
      { 
        "varName": "secondaryDudleyBrick", 
        "name": "Dudley Brick - Secondary" 
      },
      { 
        "varName": "secondaryAcocksGreen", 
        "name": "Acocks Green - Secondary" 
      },
      { 
        "varName": "secondaryCoventrySky", 
        "name": "Coventry Sky - Secondary" 
      },
      { 
        "varName": "secondaryRowleyRouge", 
        "name": "Rowley Rouge - Secondary"
			},
      {
        "varName": "gunmetalGrey",
        "name": "Gunmetal Grey"
      },
      {
        "varName": "carbonBlack",
        "name": "Carbon Black"
      }
		],
        "web": [
			{
				"varName": "primary",
				"name": "Primary Orange"
			},
			{
				"varName": "secondary",
				"name": "Secondary Grey"
			},
      {
        "varName": "primaryDark",
        "name": "Primary Orange (50% Darker)"
      },
			{
				"varName": "text",
				"name": "Text"
			},
			{
				"varName": "cta",
				"name": "Call to Action"
			},
			{
				"varName": "error",
				"name": "Error"
			},
			{
				"varName": "warning",
				"name": "Warning"
			},
			{
				"varName": "success",
				"name": "Success"
			}
		],
    "backgroundOnly": [
			{
				"varName": "background",
				"name": "Background"
			},
      {
        "varName": "backgroundAlt",
        "name": "Background Alternative"
      },
      {
        "varName": "backgroundSteelBlue",
        "name": "Background Steel Blue"
      }
		],
    "priorities": [
			{
				"varName": "priorityJobs",
				"name": "Priority Jobs"
			},
      {
        "varName": "priorityHomes",
        "name": "Priority Homes"
      },
      {
        "varName": "priorityGrowth",
        "name": "Priority Growth"
      },
      {
        "varName": "priorityJourneys",
        "name": "Priority Journeys"
      },
      {
        "varName": "priorityBannerText",
        "name": "Priority Banner Text"
      },
      {
        "varName": "priorityComplementaryJobs",
				"name": "Priority Complementary Jobs"
      },
      {
        "varName": "priorityComplementaryHomes",
        "name": "Priority Complementary Homes"
      },
      {
        "varName": "priorityComplementaryGrowth",
        "name": "Priority Complementary Growth"
      },
      {
        "varName": "priorityComplementaryJourneys",
        "name": "Priority Complementary Journeys"
      },
      {
        "varName": "prioritySecondaryJobs",
        "name": "Priority Secondary Jobs"
      },
      {
        "varName": "prioritySecondaryHomes",
        "name": "Priority Secondary Homes"
      },
      {
        "varName": "prioritySecondaryGrowth",
        "name": "Priority Secondary Growth"
      },
      {
        "varName": "prioritySecondaryJourneys",
        "name": "Priority Secondary Journeys"
      }
		],
    "programmes": [
			{
				"varName": "mayoralRegionsProgramme",
				"name": "Mayoral Regions Programme"
			},
      {
        "varName": "greenerTogether",
        "name": "Greener Together"
      }
		]
    }
  }